flask_hmac_auth/__init__.py
flask_hmac_auth/flash_hmac_auth.py
flask_hmac_auth_m4l1c3-1.1.1.dist-info/LICENSE
flask_hmac_auth_m4l1c3-1.1.1.dist-info/METADATA
flask_hmac_auth_m4l1c3-1.1.1.dist-info/WHEEL
flask_hmac_auth_m4l1c3-1.1.1.dist-info/top_level.txt
flask_hmac_auth_m4l1c3-1.1.1.dist-info/RECORD
